splitguides/__init__.py
splitguides/__main__.py
splitguides/_version.py
splitguides/build_ui.py
splitguides/exceptions.py
splitguides/hotkeys.py
splitguides/livesplit_client.py
splitguides/note_parser.py
splitguides/settings.py
splitguides/resources/logo_alpha.ico
splitguides/resources/logo_alpha.png
splitguides/server/__init__.py
splitguides/server/__main__.py
splitguides/server/split_server.py
splitguides/static/desktop.css
splitguides/static/server.css
splitguides/static/streamlistener.js
splitguides/templates/desktop.html
splitguides/templates/server.html
splitguides/ui/__init__.py
splitguides/ui/color.py
splitguides/ui/hotkey_manager.py
splitguides/ui/main.pyproject
splitguides/ui/main_window.py
splitguides/ui/server_settings_ui.py
splitguides/ui/settings_ui.py
splitguides/ui/custom_elements/__init__.py
splitguides/ui/layouts/__init__.py
splitguides/ui/layouts/main_window.ui
splitguides/ui/layouts/server_settings.ui
splitguides/ui/layouts/settings.ui
splitguides/ui/layouts/build/__init__.py
splitguides/ui/layouts/build/main_window.py
splitguides/ui/layouts/build/server_settings.py
splitguides/ui/layouts/build/settings.py
splitguides-0.10.4.dist-info/licenses/COPYING
splitguides-0.10.4.dist-info/METADATA
splitguides-0.10.4.dist-info/WHEEL
splitguides-0.10.4.dist-info/entry_points.txt
splitguides-0.10.4.dist-info/top_level.txt
splitguides-0.10.4.dist-info/RECORD
