Metadata-Version: 2.4
Name: splitguides
Version: 0.10.4
Summary: A tool for speedrunners to display notes that advance automatically with their splits in Livesplit.
Author: David C Ellis
License-Expression: GPL-3.0-or-later
Classifier: Development Status :: 4 - Beta
Classifier: Operating System :: Microsoft :: Windows
Classifier: Operating System :: POSIX :: Linux
Classifier: Programming Language :: Python :: 3.12
Classifier: Programming Language :: Python :: 3.13
Classifier: Topic :: Games/Entertainment
Requires-Python: >=3.12
License-File: COPYING
Requires-Dist: pyside6~=6.9.0
Requires-Dist: jinja2~=3.1
Requires-Dist: bleach[css]==6.0
Requires-Dist: flask~=3.0
Requires-Dist: markdown~=3.6
Requires-Dist: keyboard~=0.13.5
Requires-Dist: ducktools-classbuilder>=0.7.4
Requires-Dist: waitress~=3.0
Requires-Dist: platformdirs~=4.3
Dynamic: license-file
